tha3/__init__.py
tha3/app/__init__.py
tha3/app/ifacialmocap_puppeteer.py
tha3/app/manual_poser.py
tha3/compute/__init__.py
tha3/compute/cached_computation_func.py
tha3/compute/cached_computation_protocol.py
tha3/data/images/CC-BY-NC.txt
tha3/data/images/README.md
tha3/data/images/crypko_00.png
tha3/data/images/crypko_01.png
tha3/data/images/crypko_02.png
tha3/data/images/crypko_03.png
tha3/data/images/crypko_04.png
tha3/data/images/crypko_05.png
tha3/data/images/crypko_06.png
tha3/data/images/crypko_07.png
tha3/data/images/lambda_00.png
tha3/data/images/lambda_01.png
tha3/data/models/separable_float/editor.pt
tha3/data/models/separable_float/eyebrow_decomposer.pt
tha3/data/models/separable_float/eyebrow_morphing_combiner.pt
tha3/data/models/separable_float/face_morpher.pt
tha3/data/models/separable_float/two_algo_face_body_rotator.pt
tha3/mocap/__init__.py
tha3/mocap/ifacialmocap_constants.py
tha3/mocap/ifacialmocap_pose.py
tha3/mocap/ifacialmocap_pose_converter.py
tha3/mocap/ifacialmocap_poser_converter_25.py
tha3/mocap/ifacialmocap_v2.py
tha3/module/__init__.py
tha3/module/module_factory.py
tha3/nn/__init__.py
tha3/nn/common/__init__.py
tha3/nn/common/conv_block_factory.py
tha3/nn/common/poser_args.py
tha3/nn/common/poser_encoder_decoder_00.py
tha3/nn/common/poser_encoder_decoder_00_separable.py
tha3/nn/common/resize_conv_encoder_decoder.py
tha3/nn/common/resize_conv_unet.py
tha3/nn/conv.py
tha3/nn/editor/__init__.py
tha3/nn/editor/editor_07.py
tha3/nn/eyebrow_decomposer/__init__.py
tha3/nn/eyebrow_decomposer/eyebrow_decomposer_00.py
tha3/nn/eyebrow_decomposer/eyebrow_decomposer_03.py
tha3/nn/eyebrow_morphing_combiner/__init__.py
tha3/nn/eyebrow_morphing_combiner/eyebrow_morphing_combiner_00.py
tha3/nn/eyebrow_morphing_combiner/eyebrow_morphing_combiner_03.py
tha3/nn/face_morpher/__init__.py
tha3/nn/face_morpher/face_morpher_08.py
tha3/nn/face_morpher/face_morpher_09.py
tha3/nn/image_processing_util.py
tha3/nn/init_function.py
tha3/nn/nonlinearity_factory.py
tha3-0.1.9.dist-info/LICENSE
tha3-0.1.9.dist-info/METADATA
tha3-0.1.9.dist-info/WHEEL
tha3-0.1.9.dist-info/entry_points.txt
tha3-0.1.9.dist-info/RECORD
