Metadata-Version: 2.1
Name: tha3
Version: 0.1.9
Summary: Python package for tha3
Home-page: https://github.com/34j/tha3
License: MIT; CC-BY-4.0
Author: 34j
Author-email: 34j.95a2p@simplelogin.com
Requires-Python: >=3.8,<4.0
Classifier: Development Status :: 2 - Pre-Alpha
Classifier: Intended Audience :: Developers
Classifier: License :: Other/Proprietary License
Classifier: Natural Language :: English
Classifier: Operating System :: OS Independent
Classifier: Programming Language :: Python :: 3
Classifier: Programming Language :: Python :: 3.8
Classifier: Programming Language :: Python :: 3.9
Classifier: Programming Language :: Python :: 3.10
Classifier: Programming Language :: Python :: 3.11
Classifier: Programming Language :: Python :: 3.12
Classifier: Topic :: Software Development :: Libraries
Requires-Dist: matplotlib (>=3.7.2,<4.0.0)
Requires-Dist: torch (>=2.0.1,<3.0.0)
Requires-Dist: wxpython (>=4.2.1,<5.0.0)
Project-URL: Bug Tracker, https://github.com/34j/tha3/issues
Project-URL: Changelog, https://github.com/34j/tha3/blob/main/CHANGELOG.md
Project-URL: Documentation, https://tha3.readthedocs.io
Project-URL: Repository, https://github.com/34j/tha3
